atui/__init__.py
atui/components.py
atui/parser.py
atui/styles.py
atui-0.1.2.dist-info/METADATA
atui-0.1.2.dist-info/WHEEL
atui-0.1.2.dist-info/top_level.txt
atui-0.1.2.dist-info/RECORD
