Metadata-Version: 2.1
Name: atui
Version: 0.1.2
Summary: A UI development library with markup lenguage
Home-page: https://github.com/Lucifer13072/ATUI
Author: Lucifer
Author-email: at2823743@gmail.com
Classifier: Programming Language :: Python :: 3
Classifier: License :: OSI Approved :: MIT License
Classifier: Operating System :: OS Independent
Requires-Python: >=3.6
